kokoro_tts/__init__.py
kokoro_tts/__main__.py
kokoro_tts-2.3.0.dist-info/METADATA
kokoro_tts-2.3.0.dist-info/WHEEL
kokoro_tts-2.3.0.dist-info/entry_points.txt
kokoro_tts-2.3.0.dist-info/licenses/LICENSE
kokoro_tts-2.3.0.dist-info/RECORD
