Metadata-Version: 2.4
Name: kokoro-tts
Version: 2.3.0
Summary: A CLI text-to-speech tool using the Kokoro model, supporting multiple languages, voices (with blending), and various input formats including EPUB books and PDF documents.
Project-URL: Homepage, https://github.com/nazdridoy/kokoro-tts
Project-URL: Repository, https://github.com/nazdridoy/kokoro-tts
Project-URL: Issues, https://github.com/nazdridoy/kokoro-tts/issues
Author-email: Nazmul Hossain <nazdridoy@gmail.com>
License: MIT
License-File: LICENSE
Keywords: audio,cli,epub,kokoro,pdf,text-to-speech,tts
Classifier: Development Status :: 4 - Beta
Classifier: Intended Audience :: End Users/Desktop
Classifier: License :: OSI Approved :: MIT License
Classifier: Operating System :: OS Independent
Classifier: Programming Language :: Python :: 3
Classifier: Programming Language :: Python :: 3.9
Classifier: Programming Language :: Python :: 3.10
Classifier: Programming Language :: Python :: 3.11
Classifier: Programming Language :: Python :: 3.12
Classifier: Topic :: Multimedia :: Sound/Audio :: Speech
Classifier: Topic :: Text Processing :: Linguistic
Requires-Python: <3.13,>=3.9
Requires-Dist: beautifulsoup4>=4.12.3
Requires-Dist: ebooklib>=0.18
Requires-Dist: kokoro-onnx==0.3.9
Requires-Dist: pymupdf4llm>=0.0.17
Requires-Dist: pymupdf>=1.25.4
Requires-Dist: sounddevice>=0.5.1
Requires-Dist: soundfile>=0.13.0
